pycubedoe.py
pycubedoe-0.1.7.dist-info/AUTHORS.rst
pycubedoe-0.1.7.dist-info/LICENSE
pycubedoe-0.1.7.dist-info/METADATA
pycubedoe-0.1.7.dist-info/WHEEL
pycubedoe-0.1.7.dist-info/top_level.txt
pycubedoe-0.1.7.dist-info/RECORD
