Metadata-Version: 2.1
Name: pycubedoe
Version: 0.1.7
Summary: Generates design of experiements by constructing a nearly orthogonal latin hypercube with user-defined factors and appropriate factor ranges.
Home-page: https://github.com/jataware/pycubedoe
Author: Travis Hartman
Author-email: travis@jataware.com
License: LGPL-3.0-or-later
Project-URL: Changelog, https://github.com/jataware/pycubedoe/blob/master/CHANGELOG.md
Project-URL: Issue Tracker, https://github.com/jataware/pycubedoe/issues
Keywords: design of experiements,DOE,hypercube,latin hypercube,design point
Platform: UNKNOWN
Classifier: Development Status :: 5 - Production/Stable
Classifier: Intended Audience :: Developers
Classifier: License :: OSI Approved :: GNU Lesser General Public License v3 or later (LGPLv3+)
Classifier: Operating System :: Unix
Classifier: Operating System :: POSIX
Classifier: Operating System :: Microsoft :: Windows
Classifier: Programming Language :: Python
Classifier: Programming Language :: Python :: 3.6
Classifier: Programming Language :: Python :: 3.7
Classifier: Programming Language :: Python :: 3.8
Classifier: Programming Language :: Python :: 3.9
Classifier: Programming Language :: Python :: Implementation :: PyPy
Classifier: Topic :: Utilities
Requires-Python: >=3.6
Requires-Dist: pandas (>=0.24.2)
Provides-Extra: dev
Requires-Dist: pytest (>=3.7) ; extra == 'dev'
Requires-Dist: twine (>=3.3.0) ; extra == 'dev'
